lcdchargen/__init__.py
lcdchargen/lcdchargen.py
lcdchargen-0.1.dist-info/LICENSE
lcdchargen-0.1.dist-info/METADATA
lcdchargen-0.1.dist-info/WHEEL
lcdchargen-0.1.dist-info/entry_points.txt
lcdchargen-0.1.dist-info/top_level.txt
lcdchargen-0.1.dist-info/RECORD
